envplus/__init__.py
envplus/core.py
envplus/exceptions.py
envplus/utils.py
envplusai-0.0.3.dist-info/METADATA
envplusai-0.0.3.dist-info/WHEEL
envplusai-0.0.3.dist-info/RECORD
