Metadata-Version: 2.4
Name: envplusai
Version: 0.0.3
Summary: A lightweight Python package for managing environment variables with advanced features.
Project-URL: Homepage, https://github.com/viswa-vr-de/pyenvplus
Project-URL: Repository, https://github.com/viswa-vr-de/pyenvplus
Project-URL: Documentation, https://github.com/viswa-vr-de/pyenvplus#readme
Project-URL: Issues, https://github.com/viswa-vr-de/pyenvplus/issues
Author-email: Viswavr <viswavr54@gmail.com>
License: MIT
Keywords: 12-factor,alias,app-settings,application-config,auto-env,automation,boolean,casting,clean,cli,config,config-management,configuration,configuration-management,cross-platform,deployment,dev-tools,developer-tools,development,devops,django,dotenv,dynamic-env,easy,easy-env,env loader,env-access,env-api,env-file,env-handler,env-helper,env-interface,env-library,env-module,env-package,env-parsing,env-plus,env-processor,env-reader,env-tools,env-utils,env-var,env-vars,env-wrapper,env-writer,envi
Requires-Python: >=3.6
Requires-Dist: python-dotenv>=1.0.0
Provides-Extra: dev
Requires-Dist: pytest; extra == 'dev'
